{
  "version": 2,
  "extractor": "papercropper",
  "tables": [
    {
      "url": "assets/tables/acl-2026-findings/anthology-2026.findings-acl.1468/table-001.webp",
      "caption": "",
      "page": 0,
      "index": 1,
      "width": 1662,
      "height": 462,
      "label": "Table"
    },
    {
      "url": "assets/tables/acl-2026-findings/anthology-2026.findings-acl.1468/table-002.webp",
      "caption": "",
      "page": 0,
      "index": 2,
      "width": 1662,
      "height": 308,
      "label": "Table"
    },
    {
      "url": "assets/tables/acl-2026-findings/anthology-2026.findings-acl.1468/table-003.webp",
      "caption": "",
      "page": 0,
      "index": 3,
      "width": 1005,
      "height": 180,
      "label": "Table"
    },
    {
      "url": "assets/tables/acl-2026-findings/anthology-2026.findings-acl.1468/table-004.webp",
      "caption": "",
      "page": 0,
      "index": 4,
      "width": 807,
      "height": 222,
      "label": "Table"
    },
    {
      "url": "assets/tables/acl-2026-findings/anthology-2026.findings-acl.1468/table-005.webp",
      "caption": "",
      "page": 0,
      "index": 5,
      "width": 1663,
      "height": 500,
      "label": "Table"
    }
  ]
}